pgmob/__init__.py
pgmob/_decorators.py
pgmob/adapters/__init__.py
pgmob/adapters/base.py
pgmob/adapters/errors.py
pgmob/adapters/psycopg2.py
pgmob/backup.py
pgmob/cluster.py
pgmob/errors.py
pgmob/objects/__init__.py
pgmob/objects/databases.py
pgmob/objects/generic.py
pgmob/objects/hba_rules.py
pgmob/objects/large_objects.py
pgmob/objects/procedures.py
pgmob/objects/replication_slots.py
pgmob/objects/roles.py
pgmob/objects/schemas.py
pgmob/objects/sequences.py
pgmob/objects/tables.py
pgmob/objects/views.py
pgmob/os.py
pgmob/scripts/shell/run_postgres_command.sh
pgmob/scripts/sql/execute_os_command.sql
pgmob/scripts/sql/get_database.sql
pgmob/scripts/sql/get_large_object.sql
pgmob/scripts/sql/get_procedure.sql
pgmob/scripts/sql/get_procedure_11.sql
pgmob/scripts/sql/get_replication_slot.sql
pgmob/scripts/sql/get_role.sql
pgmob/scripts/sql/get_schema.sql
pgmob/scripts/sql/get_sequence.sql
pgmob/scripts/sql/get_table.sql
pgmob/scripts/sql/get_view.sql
pgmob/sql.py
pgmob/util.py
pgmob-0.1.3a0.dist-info/LICENSE
pgmob-0.1.3a0.dist-info/WHEEL
pgmob-0.1.3a0.dist-info/METADATA
pgmob-0.1.3a0.dist-info/RECORD
