Metadata-Version: 2.1
Name: pgmob
Version: 0.1.3a0
Summary: Postgres Managed Objects - a Postgres database management interface
Home-page: https://github.com/dataplat/pgmob/
License: MIT
Keywords: postgres,sql,backup,restore
Author: Kirill Kravtsov
Author-email: nvarscar@gmail.com
Requires-Python: >=3.9,<4
Classifier: License :: OSI Approved :: MIT License
Classifier: Operating System :: OS Independent
Classifier: Programming Language :: Python :: 3
Classifier: Programming Language :: Python :: 3.9
Classifier: Programming Language :: Python :: 3.10
Classifier: Programming Language :: Python :: 3.11
Classifier: Programming Language :: Python :: 3
Provides-Extra: psycopg2
Provides-Extra: psycopg2-binary
Requires-Dist: packaging (>=21.3)
Requires-Dist: psycopg2 (>=2.8.5,<3) ; extra == "psycopg2"
Requires-Dist: psycopg2-binary (>=2.8.5,<3) ; extra == "psycopg2-binary"
Project-URL: Documentation, https://github.com/dataplat/pgmob
Project-URL: Repository, https://github.com/dataplat/pgmob
